aws_cdk/aws_codedeploy_api/_jsii/__init__.py
aws_cdk/aws_codedeploy_api/_jsii/aws-codedeploy-api@0.33.0.jsii.tgz
aws_cdk.aws_codedeploy_api-0.33.0.dist-info/METADATA
aws_cdk.aws_codedeploy_api-0.33.0.dist-info/WHEEL
aws_cdk.aws_codedeploy_api-0.33.0.dist-info/top_level.txt
aws_cdk.aws_codedeploy_api-0.33.0.dist-info/RECORD
